README.md
setup.py
pro_search/__init__.py
pro_search/agents.py
pro_search/pro_search.py
pro_search/search.py
pro_search/test.py
pro_search.egg-info/PKG-INFO
pro_search.egg-info/SOURCES.txt
pro_search.egg-info/dependency_links.txt
pro_search.egg-info/requires.txt
pro_search.egg-info/top_level.txt