Metadata-Version: 2.1
Name: pro-search
Version: 0.2.2
Summary: An advanced web search package combining AI and web scraping
Home-page: https://github.com/PraNavKumAr01/pro_search
Author: Pranav Kumar
Author-email: pranavkumarnair@gmail.com
Classifier: License :: OSI Approved :: MIT License
Classifier: Operating System :: OS Independent
Classifier: Programming Language :: Python :: 3.7
Requires-Python: >=3.7
